ff/calculator.py
seoyoung-0.0.1.dist-info/METADATA
seoyoung-0.0.1.dist-info/WHEEL
seoyoung-0.0.1.dist-info/top_level.txt
seoyoung-0.0.1.dist-info/RECORD
