Metadata-Version: 2.1
Name: seoyoung
Version: 0.0.1
Summary: nice calculator
Home-page: https://github.com/seoyoung0501/oss25
Download-URL: https://github.com/seoyoung0501/oss25
Author: seoyoung
Classifier: Programming Language :: Python :: 3
